LicenseClassifier/__init__.py
LicenseClassifier/classifier.py
LicenseClassifier/compiled/libmatch.h
LicenseClassifier/compiled/libmatch.so
LicenseClassifier/licenses/0BSD.txt
LicenseClassifier/licenses/AFL-1.1.header.txt
LicenseClassifier/licenses/AFL-1.1.txt
LicenseClassifier/licenses/AFL-1.2.header.txt
LicenseClassifier/licenses/AFL-1.2.txt
LicenseClassifier/licenses/AFL-2.0.header.txt
LicenseClassifier/licenses/AFL-2.0.txt
LicenseClassifier/licenses/AFL-2.1.header.txt
LicenseClassifier/licenses/AFL-2.1.txt
LicenseClassifier/licenses/AFL-3.0.header.txt
LicenseClassifier/licenses/AFL-3.0.txt
LicenseClassifier/licenses/AGPL-1.0.txt
LicenseClassifier/licenses/AGPL-3.0.header.txt
LicenseClassifier/licenses/AGPL-3.0.txt
LicenseClassifier/licenses/AML.txt
LicenseClassifier/licenses/AMPAS.txt
LicenseClassifier/licenses/APSL-1.0.header.txt
LicenseClassifier/licenses/APSL-1.0.txt
LicenseClassifier/licenses/APSL-1.1.header.txt
LicenseClassifier/licenses/APSL-1.1.txt
LicenseClassifier/licenses/APSL-1.2.header.txt
LicenseClassifier/licenses/APSL-1.2.txt
LicenseClassifier/licenses/APSL-2.0.header.txt
LicenseClassifier/licenses/APSL-2.0.txt
LicenseClassifier/licenses/Apache-1.0.txt
LicenseClassifier/licenses/Apache-1.1.txt
LicenseClassifier/licenses/Apache-2.0.header.txt
LicenseClassifier/licenses/Apache-2.0.txt
LicenseClassifier/licenses/Artistic-1.0-Perl.txt
LicenseClassifier/licenses/Artistic-1.0-cl8.txt
LicenseClassifier/licenses/Artistic-1.0.txt
LicenseClassifier/licenses/Artistic-2.0.txt
LicenseClassifier/licenses/Atmel.txt
LicenseClassifier/licenses/BCL.txt
LicenseClassifier/licenses/BSD-2-Clause-FreeBSD.txt
LicenseClassifier/licenses/BSD-2-Clause-NetBSD.txt
LicenseClassifier/licenses/BSD-2-Clause.txt
LicenseClassifier/licenses/BSD-3-Clause-Attribution.txt
LicenseClassifier/licenses/BSD-3-Clause-Clear.txt
LicenseClassifier/licenses/BSD-3-Clause-LBNL.txt
LicenseClassifier/licenses/BSD-3-Clause.txt
LicenseClassifier/licenses/BSD-3-Clause_sun.txt
golicense_classifier-0.0.16.dist-info/LICENSE
golicense_classifier-0.0.16.dist-info/METADATA
golicense_classifier-0.0.16.dist-info/WHEEL
golicense_classifier-0.0.16.dist-info/top_level.txt
golicense_classifier-0.0.16.dist-info/RECORD
